muko/__init__.py
muko/ai.cp310-win_amd64.pyd
muko/ai.cpython-310-darwin.so
muko/animation.cp310-win_amd64.pyd
muko/animation.cpython-310-darwin.so
muko/core.cp310-win_amd64.pyd
muko/core.cpython-310-darwin.so
muko/designer.cp310-win_amd64.pyd
muko/designer.cpython-310-darwin.so
muko/logo.png
muko/media.cp310-win_amd64.pyd
muko/media.cpython-310-darwin.so
muko/mix.cp310-win_amd64.pyd
muko/mix.cpython-310-darwin.so
muko/ui.cp310-win_amd64.pyd
muko/ui.cpython-310-darwin.so
muko/font/default.otf
muko/themes/__init__.py
muko/themes/theme_1.json
muko/themes/theme_2.json
muko/themes/theme_3.json
muko-4.77.dist-info/LICENSE
muko-4.77.dist-info/METADATA
muko-4.77.dist-info/WHEEL
muko-4.77.dist-info/entry_points.txt
muko-4.77.dist-info/top_level.txt
muko-4.77.dist-info/RECORD
