Metadata-Version: 2.1
Name: muko
Version: 4.77
Summary: 加速实现AIGC、自动办公的中文编程工具
Home-page: https://www.mikooo.cn
Author: Milk
Author-email: 719496375@qq.com
License: The MIT License
Platform: win64
Classifier: Programming Language :: Python :: 3.10
Classifier: License :: OSI Approved :: MIT License
Classifier: Operating System :: Microsoft :: Windows
Requires-Python: ==3.10.*
License-File: LICENSE
Requires-Dist: requests>=2.31.0
Requires-Dist: moviepy>=1.0.3
Requires-Dist: pillow==11.0.0
Requires-Dist: psd-tools==1.10.2
Requires-Dist: diskcache>=5.6.3
Requires-Dist: retrying>=1.3.3
Requires-Dist: numpy==1.23.4
Requires-Dist: opencv-python>=4.8.1.78
Requires-Dist: diplib<=3.4.3
Requires-Dist: rembg>=2.0.56
Requires-Dist: easyocr==1.7.1
Requires-Dist: pydub>=0.25.1
Requires-Dist: pygame-gui>=0.6.12
Requires-Dist: librosa>=0.10.0
Requires-Dist: soundfile>=0.12.1
Requires-Dist: python-bidi==0.4.2
Requires-Dist: pyroomacoustics>=0.7.6
Requires-Dist: matplotlib>=3.7.4
Requires-Dist: scipy>=1.10.1
Requires-Dist: oss2>=2.18.4
Requires-Dist: pedalboard==0.9.6
Requires-Dist: websocket-client>=1.8.0
Requires-Dist: requests-toolbelt
Requires-Dist: einops
Requires-Dist: transformers>=4.28.1
Requires-Dist: tokenizers>=0.13.3
Requires-Dist: sentencepiece
Requires-Dist: safetensors>=0.4.2
Requires-Dist: aiohttp
Requires-Dist: pyyaml
Requires-Dist: tqdm
Requires-Dist: psutil
Requires-Dist: torch<=2.4.1
Requires-Dist: torchvision
Requires-Dist: torchaudio
Requires-Dist: torchsde
Requires-Dist: kornia>=0.7.1
Requires-Dist: spandrel
Requires-Dist: simpleeval
Requires-Dist: wmi
Requires-Dist: cn2an==0.5.23
Requires-Dist: pyzipper
